regtag/__init__.py
regtag/abb_dict.json
regtag/augment.py
regtag/clean_text.py
regtag/domain_extension.json
regtag/domain_names.json
regtag/en_dict.json
regtag/general_word_en.txt
regtag/main.py
regtag/reabb.py
regtag/redate.py
regtag/reid.py
regtag/renumbers.py
regtag/renumberscales.py
regtag/reoov.py
regtag/vidict.txt
regtag-0.4.0.1.dist-info/LICENSE
regtag-0.4.0.1.dist-info/METADATA
regtag-0.4.0.1.dist-info/WHEEL
regtag-0.4.0.1.dist-info/top_level.txt
regtag-0.4.0.1.dist-info/RECORD
