Metadata-Version: 2.1
Name: regtag
Version: 0.4.0.1
Summary: Regex Tagging
Home-page: https://github.com/nguyenvulebinh/regtag
Author: Binh Nguyen
Author-email: nguyenvulebinh@gmail.com
License: MIT
Project-URL: Bug Tracker, https://github.com/nguyenvulebinh/regtag/issues
Platform: UNKNOWN
Classifier: License :: OSI Approved :: MIT License
Classifier: Programming Language :: Python :: 3
Classifier: Programming Language :: Python :: 3.7
Requires-Python: >=3.6
License-File: LICENSE
Requires-Dist: nltk (>=3.6.5)
Requires-Dist: validators (>=0.18.2)
